example_pkg/__init__.py
example_pkg/switch.py
tests/__init__.py
tests/test_switch.py
pip_example_pkg_revuel-0.10.3.dist-info/LICENSE
pip_example_pkg_revuel-0.10.3.dist-info/METADATA
pip_example_pkg_revuel-0.10.3.dist-info/WHEEL
pip_example_pkg_revuel-0.10.3.dist-info/dependency_links.txt
pip_example_pkg_revuel-0.10.3.dist-info/top_level.txt
pip_example_pkg_revuel-0.10.3.dist-info/RECORD
