Metadata-Version: 2.1
Name: pip-example-pkg-revuel
Version: 0.10.3
Summary: Tutorial to distribute a pip package
Home-page: https://github.com/revuel/pip-example-pkg-revule
Author: revuel
Author-email: revuel22@hotmail.com
License: UNKNOWN
Platform: UNKNOWN
Classifier: Programming Language :: Python :: 3
Classifier: License :: Other/Proprietary License
Classifier: Operating System :: OS Independent
Requires-Python: >=3.7
Requires-Dist: spacy (==2.3.0)
Requires-Dist: en-core-web-sm
